MANIFEST.in
README.rst
requirements.txt
setup.py
vanilla/__init__.py
vanilla/bean.py
vanilla.bean.egg-info/PKG-INFO
vanilla.bean.egg-info/SOURCES.txt
vanilla.bean.egg-info/dependency_links.txt
vanilla.bean.egg-info/namespace_packages.txt
vanilla.bean.egg-info/requires.txt
vanilla.bean.egg-info/top_level.txt