Metadata-Version: 1.0
Name: vanilla.bean
Version: 0.1.3
Summary: Obligatory Sinatra style (but concurrent!) micro-web framework for Vanilla.
Home-page: https://github.com/cablehead/vanilla.bean
Author: Andy Gayton
Author-email: andy@thecablelounge.com
License: MIT
Platform: UNKNOWN
